[
  {
    "id": 1,
    "name": "Dibujo",
    "desc": "Dibujo de Furina hecho especialmente para ti",
    "price": 800,
    "stock": 1,
    "image": "https://images.unsplash.com/photo-1559339352-11d035aa65de?auto=format&fit=crop&w=400&q=80"
  },
  {
    "id": 2,
    "name": "Dibujo",
    "desc": "Dibujo de Hu Tao hecho especialmente para ti",
    "price": 250,
    "stock": 1,
    "image": "https://wallpapercave.com/wp/wp5924545.jpg"
  },
  {
    "id": 3,
    "name": "Crunchyroll",
    "desc": "Cuenta compartida",
    "price": 150,
    "stock": 1,
    "image": "https://images.unsplash.com/photo-1489599849927-2ee91cede3ba?auto=format&fit=crop&w=400&q=80"
  }
]
